busybee/__init__.py
busybee/_busybee.py
busybee/_string_helpers.py
tests/__init__.py
tests/context.py
tests/test_internals.py
tests/test_public_api.py
tests/test_string_helpers.py
busybee-1.0.0.dist-info/LICENSE
busybee-1.0.0.dist-info/METADATA
busybee-1.0.0.dist-info/WHEEL
busybee-1.0.0.dist-info/top_level.txt
busybee-1.0.0.dist-info/RECORD
