Metadata-Version: 2.1
Name: busybee
Version: 1.0.0
Summary: Simple and interactive multi-processing for Python and notebooks
Home-page: https://github.com/lambdapioneer/busybee
Author: Daniel H
Author-email: not_provided@example.org
License: UNKNOWN
Platform: UNKNOWN
Classifier: Programming Language :: Python :: 3
Classifier: Operating System :: OS Independent
Classifier: License :: OSI Approved :: MIT License
Classifier: Development Status :: 5 - Production/Stable
Requires-Python: >=3.6
